{
	"configurations" : 
	[
		{
			"directories" : 
			[
				{
					"build" : ".",
					"hasInstallRule" : true,
					"jsonFile" : "directory-.-3f25eeab201a2f24f653.json",
					"minimumCMakeVersion" : 
					{
						"string" : "3.20"
					},
					"projectIndex" : 0,
					"source" : ".",
					"targetIndexes" : 
					[
						0,
						1
					]
				}
			],
			"name" : "",
			"projects" : 
			[
				{
					"directoryIndexes" : 
					[
						0
					],
					"name" : "rmf_demos_gz",
					"targetIndexes" : 
					[
						0,
						1
					]
				}
			],
			"targets" : 
			[
				{
					"directoryIndex" : 0,
					"id" : "rmf_demos_gz_uninstall::@6890427a1f51a3e7e1df",
					"jsonFile" : "target-rmf_demos_gz_uninstall-0fd5643dfd4bef1f589d.json",
					"name" : "rmf_demos_gz_uninstall",
					"projectIndex" : 0
				},
				{
					"directoryIndex" : 0,
					"id" : "uninstall::@6890427a1f51a3e7e1df",
					"jsonFile" : "target-uninstall-db6af68f2b870e55f9f2.json",
					"name" : "uninstall",
					"projectIndex" : 0
				}
			]
		}
	],
	"kind" : "codemodel",
	"paths" : 
	{
		"build" : "/ws/build/rmf_demos_gz",
		"source" : "/ws/src/rmf_demos/rmf_demos_gz"
	},
	"version" : 
	{
		"major" : 2,
		"minor" : 6
	}
}
